odoo/addons/base_import_pdf_by_template/README.rst
odoo/addons/base_import_pdf_by_template/__init__.py
odoo/addons/base_import_pdf_by_template/__manifest__.py
odoo/addons/base_import_pdf_by_template/demo/base_import_pdf_template.xml
odoo/addons/base_import_pdf_by_template/i18n/base_import_pdf_by_template.pot
odoo/addons/base_import_pdf_by_template/i18n/es.po
odoo/addons/base_import_pdf_by_template/i18n/it.po
odoo/addons/base_import_pdf_by_template/models/__init__.py
odoo/addons/base_import_pdf_by_template/models/base_import_pdf_template.py
odoo/addons/base_import_pdf_by_template/readme/CONFIGURE.md
odoo/addons/base_import_pdf_by_template/readme/CONTRIBUTORS.md
odoo/addons/base_import_pdf_by_template/readme/DESCRIPTION.md
odoo/addons/base_import_pdf_by_template/readme/ROADMAP.md
odoo/addons/base_import_pdf_by_template/readme/USAGE.md
odoo/addons/base_import_pdf_by_template/security/ir.model.access.csv
odoo/addons/base_import_pdf_by_template/security/security.xml
odoo/addons/base_import_pdf_by_template/static/description/icon.png
odoo/addons/base_import_pdf_by_template/static/description/index.html
odoo/addons/base_import_pdf_by_template/static/src/js/import_menu.esm.js
odoo/addons/base_import_pdf_by_template/static/src/xml/import_records.xml
odoo/addons/base_import_pdf_by_template/tests/__init__.py
odoo/addons/base_import_pdf_by_template/tests/test_base_import_pdf_by_template.py
odoo/addons/base_import_pdf_by_template/tests/data/res-partner.pdf
odoo/addons/base_import_pdf_by_template/views/base_import_pdf_template_line_views.xml
odoo/addons/base_import_pdf_by_template/views/base_import_pdf_template_views.xml
odoo/addons/base_import_pdf_by_template/wizards/__init__.py
odoo/addons/base_import_pdf_by_template/wizards/wizard_base_import_pdf_mixin.py
odoo/addons/base_import_pdf_by_template/wizards/wizard_base_import_pdf_preview.py
odoo/addons/base_import_pdf_by_template/wizards/wizard_base_import_pdf_preview_views.xml
odoo_addon_base_import_pdf_by_template-17.0.1.2.8.3.dist-info/METADATA
odoo_addon_base_import_pdf_by_template-17.0.1.2.8.3.dist-info/WHEEL
odoo_addon_base_import_pdf_by_template-17.0.1.2.8.3.dist-info/top_level.txt
odoo_addon_base_import_pdf_by_template-17.0.1.2.8.3.dist-info/RECORD
